mrfitty/__init__.py
mrfitty/__main__.py
mrfitty/_version.py
mrfitty/base.py
mrfitty/combination_fit.py
mrfitty/database.py
mrfitty/fit_task_builder.py
mrfitty/linear_model.py
mrfitty/loss.py
mrfitty/plot.py
mrfitty/prediction_error_fit.py
mrfitty/tests/__init__.py
mrfitty/tests/conftest.py
mrfitty/tests/test_arsenic_fit.py
mrfitty/tests/test_combination_fit.py
mrfitty/tests/test_database.py
mrfitty/tests/test_energy_range_builder.py
mrfitty/tests/test_fit_task_builder.py
mrfitty/tests/test_mrfitty.py
mrfitty/tests/test_prediction_error_fit.py
mrfitty/tests/test_spectrum.py
mrfitty/tests/test_spectrum_fit.py
mrfitty-0.14.0.dist-info/AUTHORS.md
mrfitty-0.14.0.dist-info/LICENSE
mrfitty-0.14.0.dist-info/METADATA
mrfitty-0.14.0.dist-info/WHEEL
mrfitty-0.14.0.dist-info/entry_points.txt
mrfitty-0.14.0.dist-info/top_level.txt
mrfitty-0.14.0.dist-info/RECORD
