Metadata-Version: 2.1
Name: mrfitty
Version: 0.14.0
Summary: Linear least-squares fitting for XANES data.
Home-page: https://github.com/jklynch/mr-fitty
Author: Joshua Lynch
Author-email: joshua.kevin.lynch@gmail.com
License: MIT
Platform: UNKNOWN
Classifier: Development Status :: 4 - Beta
Classifier: Environment :: Console
Classifier: Intended Audience :: Science/Research
Classifier: License :: OSI Approved :: MIT License
Classifier: Natural Language :: English
Classifier: Programming Language :: Python :: 3
Requires-Python: >=3.8
License-File: LICENSE
License-File: AUTHORS.md
Requires-Dist: jupyter
Requires-Dist: matplotlib
Requires-Dist: numpy
Requires-Dist: pandas
Requires-Dist: scipy
Requires-Dist: scikits.bootstrap
Requires-Dist: scikit-learn
Requires-Dist: sqlalchemy
